livealert/__init__.py
livealert/cli.py
livealert/config.py
livealert/news.py
livealert/weather.py
livealert-0.1.4.dist-info/licenses/LICENSE
livealert-0.1.4.dist-info/METADATA
livealert-0.1.4.dist-info/WHEEL
livealert-0.1.4.dist-info/entry_points.txt
livealert-0.1.4.dist-info/top_level.txt
livealert-0.1.4.dist-info/RECORD
