Metadata-Version: 2.4
Name: livealert
Version: 0.1.4
Summary: A CLI tool to fetch real-time weather and news alerts
Home-page: https://github.com/cyrus-spc-tech/livealert
Author: cyrus-spc-tech
Author-email: tanishgupta12389@gmail.com
License: # MIT License
Classifier: Programming Language :: Python :: 3
Classifier: License :: OSI Approved :: MIT License
Classifier: Operating System :: OS Independent
Requires-Python: >=3.7
License-File: LICENSE
Requires-Dist: click>=8.0.0
Requires-Dist: requests>=2.25.1
Requires-Dist: python-dotenv>=0.19.0
Requires-Dist: rich>=12.0.0
Requires-Dist: pyfiglet>=0.8.post1
Dynamic: author
Dynamic: author-email
Dynamic: classifier
Dynamic: description
Dynamic: description-content-type
Dynamic: home-page
Dynamic: license
Dynamic: license-file
Dynamic: requires-dist
Dynamic: requires-python
Dynamic: summary
